localpost-0.4.0.dist-info/METADATA
localpost-0.4.0.dist-info/WHEEL
localpost-0.4.0.dist-info/entry_points.txt
localpost-0.4.0.dist-info/licenses/LICENSE
localpost/.gitignore
localpost/__init__.py
localpost/__meta__.py
localpost/_debug.py
localpost/_otel_utils.py
localpost/_run.py
localpost/_utils.py
localpost/consumers/__init__.py
localpost/consumers/kafka.py
localpost/consumers/kafka_otel.py
localpost/consumers/kafka_protobuf.py
localpost/consumers/sqs.py
localpost/consumers/sqs_otel.py
localpost/consumers/stream.py
localpost/consumers/stream_otel.py
localpost/flow/__init__.py
localpost/flow/_batching.py
localpost/flow/_flow.py
localpost/flow/_ops.py
localpost/hosting/__init__.py
localpost/hosting/_app_host.py
localpost/hosting/_host.py
localpost/hosting/grpc.py
localpost/hosting/http.py
localpost/hosting/middlewares.py
localpost/py.typed
localpost/scheduler/__init__.py
localpost/scheduler/_cond.py
localpost/scheduler/_scheduler.py
localpost/scheduler/_trigger.py
localpost/scheduler/cond/__init__.py
localpost/scheduler/cond/cron.py
localpost-0.4.0.dist-info/RECORD
